ai_api_docs/__init__.py
ai_api_docs/cli.py
ai_api_test_docs-1.0.1.dist-info/LICENSE
ai_api_test_docs-1.0.1.dist-info/METADATA
ai_api_test_docs-1.0.1.dist-info/WHEEL
ai_api_test_docs-1.0.1.dist-info/entry_points.txt
ai_api_test_docs-1.0.1.dist-info/top_level.txt
ai_api_test_docs-1.0.1.dist-info/RECORD
