Metadata-Version: 2.1
Name: ai-api-test-docs
Version: 1.0.1
Summary: AI-powered API test and documentation generator using Gemini
Author: Ezeana Micheal
License: MIT
Requires-Python: >=3.9
License-File: LICENSE
Requires-Dist: google-generativeai>=0.6.9
Requires-Dist: python-dotenv>=1.0.0
